{
    "moduleName": "Langue",
    "changingTitle": "Je change ta langue maintenant...",
    "changedToTitle": "Changed your language to English!",
    "errorTitle": "Cette langue n'existe pas ou elle n'est pas complètement traduite!",
    "errorDescription": "Ta langue n'a pas été changée. Ces langues sont actuellement disponibles (ne signifie pas qu'elles sont traduites):",
    "current1": "Your language preference is set to ",
    "current2": ".",
    "executedBy": "Exécuté par ",
    "credits": "Proofread by <@PUT_YOUR_DISCORD_ID_IN_HERE>.",
    "ar": "Arabe",
    "bg": "Bulgare",
    "zhcn": "Chinois (Simplifié)",
    "zhtw": "Chinois (Traditionnel)",
    "cs": "Tchèque",
    "da": "Danois",
    "nl": "Hollandais",
    "fi": "Finlandais",
    "fr": "Français",
    "de": "Allemand",
    "em": "Emoji",
    "en": "Anglais",
    "el": "Grec",
    "ib": "Inhale Banana",
    "it": "Italien",
    "ja": "Japonais",
    "ko": "Coréen",
    "no": "Norvégien",
    "enpt": "Anglais Pirate",
    "pl": "Polonais",
    "pt": "Portugais",
    "ptbr": "Portugais (Brésil)",
    "ru": "Russe",
    "es": "Espagnol",
    "espe": "Espagnol (Pérou)",
    "he": "Hébreu",
    "sv": "Suédois",
    "th": "Thaï",
    "tr": "Turc",
    "ua": "Ukrainien"
}