{
	"moduleName": "Språk",
	"changedToTitle": "Ditt språk har ändrats till svenska!",
	"resetTitle": "Reset your language!",
	"didntChange": "Ditt språk ändrades inte",
	"alreadyThis": "This happened because you chose a language that already was your language preference.",
	"notSet": "This happened because you hadn't set a language to begin with.",
	"notTranslated": "The language you tried to select isn't translated enough for it to be chosen. If you speak this language, you can find out how to help translate it by using `/translate`.",
	"errorTitle": "Detta språk har ännu inte lagts till!",
	"errorDescription": "Your language hasn't been changed. These languages are currently available (this doesn't mean they're translated):",
	"suggestAdd": "If you'd like to have this language added to the bot, please contact an administrator.",
	"listTitle": "Lista över språk",
	"listElement": "`%%code%%` | **%%language%%**",
	"credits": "Found an issue? Report it using `/feedback`.",
	"ar": "Arabiska",
	"bg": "Bulgariska",
	"zhcn": "Kinesiska (förenklad)",
	"zhtw": "Kinesiska (traditionell)",
	"cs": "Tjeckiska",
	"da": "Danska",
	"nl": "Nederländska",
	"en": "Engelska",
	"fil": "Filippinska",
	"fi": "Finska",
	"fr": "Franska",
	"de": "Tyska",
	"el": "Grekiska",
	"he": "Hebreiska",
	"hi": "Hindi",
	"hu": "Ungerska",
	"id": "Indonesiska",
	"ib": "Inhale Banana",
	"it": "Italienska",
	"ja": "Japanska",
	"ko": "Koreanska",
	"ms": "Malajiska",
	"no": "Norska",
	"fa": "Persian",
	"enpt": "Piratengelska",
	"pl": "Polska",
	"pt": "Portugisiska",
	"ptbr": "Portugisiska (brasiliansk)",
	"ro": "Rumänska",
	"ru": "Ryska",
	"es": "Spanska",
	"esmx": "Spanska (mexikansk)",
	"espe": "Spanska (peruansk)",
	"sv": "Svenska",
	"th": "Thailändska",
	"tr": "Turkiska",
	"ua": "Ukrainska"
}
