{
	"moduleName": "Estatísticas do Minecraft",
	"history": {
		"firstName": "Primeiro nome",
		"nameHistoryFor": "Histórico de nomes de %%username%%",
		"youChangedName": "Você {number, plural, =0 {nunca mudou seu nome} one {mudou seu nome # vez} other {mudou seu nome # vezes}}.",
		"userChangedName": "%%username%% {number, plural, =0 {nunca mudou de nome} one {mudou de nome # vez} other {mudou de nome # vezes}}."
	},
	"skin": {
		"yourSkin": "Aqui está a sua skin!",
		"userSkin": "Aqui está a skin de %%user%%!",
		"isLinked": "Este jogador está vinculado com %%user%%"
	}
}
