{
	"moduleName": "Minecraft-tilastot",
	"history": {
		"firstName": "Ensimmäinen nimi",
		"nameHistoryFor": "Käyttäjän %%username%% nimihistoria",
		"youChangedName": "{number, plural, =0 {Et ole koskaan vaihtanut nimeäsi} one {Olet vaihtanut nimesi # kerran} other {Olet vaihtanut nimesi # kertaa}}.",
		"userChangedName": "%%username%% {number, plural, =0 {ei ole koskaan vaihtanut nimeään} one {on vaihtanut nimensä # kerran} other {on vaihtanut nimensä # kertaa}}."
	},
	"skin": {
		"yourSkin": "Tässä on skinisi!",
		"userSkin": "Tässä on käyttäjän %%user%% skini!",
		"isLinked": "Tämä on käyttäjän %%user%% Minecraft-käyttäjä"
	}
}
