{
    "moduleName": "Käännösprojektit",
    "allProjects": "Tässä ovat kaikki projektit, joita tällä hetkellä tuemme palvelimellamme!",
    "description": "Jos olet jo mukana jossain näistä projekteista, mutta sinulla ei ole vielä rooleja, käytä komentoa `+reverify [profiilin URL]` saadaksesi ne!",
    "projectInfo": "Löyät linkin projektiin %%project%% [täältä](%%link%%). Saadaksesi lisätietoa käytä komentoa %%command%%.",
    "alreadyJoined": "Olet jo liittynyt tähän projektiin!",
    "notJoined": "Et ole vielä liittynyt tähän projektiin!",
    "dmError": "Emme voineet tarkistaa oletko mukana tässä projektissa vai et. Tehdäksesi tämän sinun tulee suorittaa komento Hypixelin kääntäjien yhteisön Discord-palvelimella."
}