{
    "moduleName": "Gebuikersinformatie",
    "userID": "%%user%% (ID: %%id%%)",
    "userNotFound": "Die gebruiker kon niet worden gevonden!",
    "uperms": "Rechten",
    "uroles": "Rollen",
    "ujoined": "Lid geworden op",
    "ucreated": "Account aangemaakt op",
    "timeAgo": "%%time%% %%unit%% geleden",
    "time": {
        "second": "seconde",
        "seconds": "seconden",
        "minute": "minute",
        "minutes": "minuten",
        "hour": "hour",
        "hours": "hours",
        "day": "day",
        "days": "days",
        "month": "month",
        "months": "months",
        "year": "year",
        "years": "years"
    },
    "dateLocale": "nl-NL",
    "timeZone": "Europe/Amsterdam",
    "notes": "Notes",
    "owner": "Discord Owner",
    "coOwner": "Discord Co-Owner",
    "admin": "Discord Administrator",
    "mod": "Discord Moderator",
    "helper": "Discord Helper",
    "manager": "Project Manager",
    "executedBy": "Uitgevoerd door %%user%%"
}