{
    "moduleName": "Jazyk",
    "changedToTitle": "Tvůj jazyk byl změněn na češtinu!",
    "didntChange": "Tvůj jazyk se nezměnil",
    "alreadyThis": "Toto se stalo, protože jazyk, který jsi zvolil, už jsi měl nastavený.",
    "errorTitle": "Tento jazyk zatím nebyl přidán!",
    "errorDescription": "Tvůj jazyk nebyl změněn. Momentálně jsou dostupné tyto jazyky (to neznamená, že jsou přeložené):",
    "suggestAdd": "Pokud bys chtěl, aby byl přidán tvůj jazyk, kontaktuj prosím vedení serveru nebo napiš návrh pomocí `+language add <jazyk>`.",
    "current": "Tvoje předvolba jazyka je nastavena na češtinu.",
    "request": "Úspěšně jsi požádal o přidání tohoto jazyka:",
    "errorRequest": "Při žádání o přidání tohoto jazyka došlo k chybě",
    "errorRequestDesc": "Nepodařilo se nám najít jazyk, o jehož přidání jsi chtěl požádat. Pokud se domníváš, že je to chyba, napiš botovi soukromou zprávu s žádostí.",
    "listTitle": "Seznam jazyků",
    "listElement": "`%%code%%` | **%%language%%**",
    "credits": "Našel jsi chybu? Nahlas ji pomocí `+issue`.",
    "ar": "Arabština",
    "bar": "Bavorština",
    "bg": "Bulharština",
    "zhcn": "Čínština (zjednodušená)",
    "zhtw": "Čínština (tradiční)",
    "cs": "Čeština",
    "da": "Dánština",
    "nl": "Nizozemština",
    "fi": "Finština",
    "fr": "Francouzština",
    "de": "Němčina",
    "en": "Angličtina",
    "el": "Řečtina",
    "hu": "Maďarština",
    "ib": "Inhale Banana",
    "id": "Indonéština",
    "it": "Italština",
    "ja": "Japonština",
    "ko": "Korejština",
    "lol": "LOLCAT",
    "ms": "Malajština",
    "no": "Norština",
    "enpt": "Pirátská angličtina",
    "pl": "Polština",
    "pt": "Portugalština",
    "ptbr": "Portugalština (brazilská)",
    "ru": "Ruština",
    "es": "Španělština",
    "esmx": "Španělština (mexická)",
    "espe": "Španělština (peruánská)",
    "he": "Hebrejština",
    "sv": "Švédština",
    "th": "Thajština",
    "tr": "Turečtina",
    "ua": "Ukrajinština"
}