{
	"moduleName": "Sprog",
	"changedToTitle": "Skiftede dit sprog til Dansk!",
	"resetTitle": "Reset your language!",
	"didntChange": "Dit sprog blev ikke ændret",
	"alreadyThis": "Dette skete fordi du valgte et sprog der allerede var din sprogpræference.",
	"notSet": "This happened because you hadn't set a language to begin with.",
	"notTranslated": "The language you tried to select isn't translated enough for it to be chosen. If you speak this language, you can find out how to help translate it by using `/translate`.",
	"errorTitle": "Dette sprog er ikke blevet tilføjet endnu!",
	"errorDescription": "Dit sprog er ikke blevet ændret. Disse sprog er i øjeblikket tilgængelig (Det betyder ikke, at de er oversat):",
	"suggestAdd": "If you'd like to have this language added to the bot, please contact an administrator.",
	"listTitle": "Liste over sprog",
	"credits": "Found an issue? Report it using `/feedback`.",
	"ar": "Arabisk",
	"bg": "Bulgarsk",
	"zh_CN": "Kinesisk (forenklet)",
	"zh_TW": "Kinesisk (traditionelt)",
	"hr": "Kroatisk",
	"cs": "Tjekkisk",
	"da": "Dansk",
	"nl": "Hollandsk",
	"en": "Engelsk",
	"fil": "Filippinsk",
	"fi": "Finsk",
	"fr": "Fransk",
	"de": "Tysk",
	"el": "Græsk",
	"he": "Hebraisk",
	"hi": "Hindi",
	"hu": "Ungarsk",
	"id": "Indonesisk",
	"ib": "Inhale Banana",
	"it": "Italiensk",
	"ja": "Japansk",
	"ko": "Koreansk",
	"lt": "Litauisk",
	"ms": "Malaysisk",
	"no": "Norsk",
	"fa": "Persian",
	"en_PT": "Piratengelsk",
	"pl": "Polsk",
	"pt_PT": "Portugisisk",
	"pt_BR": "Portugisisk (Brasilien)",
	"ro": "Rumænsk",
	"ru": "Russisk",
	"es_ES": "Spansk",
	"es_MX": "Spansk (Mexico)",
	"es_PE": "Spansk (Peru)",
	"sv_SE": "Svensk",
	"th": "Thai",
	"tr": "Tyrkisk",
	"uk": "Ukrainsk",
	"vi": "Vietnamesisk"
}
