{
    "tip": "Tip",
    "tips": {
        "0": "Har du prøvet Inhale Banana-sproget? Skift dit sprog til det ved at skrive `+lang ib`!",
        "1": "I need translators! Find out how to become a bot translator at %%translate%%.",
        "2": "Har du prøvet Emoji-sproget? Skift dit sprog til det ved at skrive `+lang em`!",
        "3": "Skift venligst dine links til en-en!",
        "4": "Du får tilfældigt antal XP hvert minut, hvis du chatter, der eventuelt kan få dig op i niveau.",
        "5": "Vi har brug for flere tips! Indsend dem ved at skrive `+feedback`.",
        "6": "Vidste du, at vi har en guide på hvordan man kommer godt i gang med Crowdin? Tjek den ud i %%gettingStarted%%. Den har nogle brugbare tips!",
        "7": "Have you followed our twitter account? Check it out at %%twitter%%!",
        "8": "%%rules%% og %%serverInfo%% har al den info, du har brug for på denne server!",
        "9": "Har du fundet en fejl i en oversættelse? Kontakt sprogets korrekturlæser eller fortæl folk det i en oversættelseskanal.",
        "10": "Did you know most channels have important information pinned? You should check it out every time you visit one!"
    },
    "executedBy": "Udført af %%user%%"
}